ubireader/__init__.py
ubireader/debug.py
ubireader/scripts/__init__.py
ubireader/scripts/ubireader_display_blocks.py
ubireader/scripts/ubireader_display_info.py
ubireader/scripts/ubireader_extract_files.py
ubireader/scripts/ubireader_extract_images.py
ubireader/scripts/ubireader_list_files.py
ubireader/scripts/ubireader_utils_info.py
ubireader/settings.py
ubireader/ubi/__init__.py
ubireader/ubi/block/__init__.py
ubireader/ubi/block/layout.py
ubireader/ubi/block/sort.py
ubireader/ubi/defines.py
ubireader/ubi/display.py
ubireader/ubi/headers.py
ubireader/ubi/image.py
ubireader/ubi/volume.py
ubireader/ubi_io.py
ubireader/ubifs/__init__.py
ubireader/ubifs/decrypt.py
ubireader/ubifs/defines.py
ubireader/ubifs/display.py
ubireader/ubifs/list.py
ubireader/ubifs/misc.py
ubireader/ubifs/nodes.py
ubireader/ubifs/output.py
ubireader/ubifs/walk.py
ubireader/utils.py
ubi_reader-0.8.12.dist-info/LICENSE
ubi_reader-0.8.12.dist-info/METADATA
ubi_reader-0.8.12.dist-info/WHEEL
ubi_reader-0.8.12.dist-info/entry_points.txt
ubi_reader-0.8.12.dist-info/RECORD
