Metadata-Version: 2.1
Name: ubi-reader
Version: 0.8.12
Summary: Extract files from UBI and UBIFS images.
License: GNU GPL
Author: ONEKEY
Author-email: support@onekey.com
Requires-Python: >=3.9.2
Classifier: License :: Other/Proprietary License
Classifier: Programming Language :: Python :: 3
Classifier: Programming Language :: Python :: 3.10
Classifier: Programming Language :: Python :: 3.11
Classifier: Programming Language :: Python :: 3.12
Classifier: Programming Language :: Python :: 3.13
Requires-Dist: cryptography (>=44.0.2,<45.0.0)
Requires-Dist: lzallright (>=0.2.1,<0.3.0)
